tryon_tray/__init__.py
tryon_tray/base.py
tryon_tray/vton_api.py
tryon_tray/api/alphabake.py
tryon_tray/api/video_gen.py
tryon_tray/api/vmodel.py
tryon_tray/api/vton.py
tryon_tray/base/__init__.py
tryon_tray/base/service.py
tryon_tray/base/video.py
tryon_tray/base/vton.py
tryon_tray/services/factory.py
tryon_tray/services/obsolete/fashnai.py
tryon_tray/services/obsolete/klingai.py
tryon_tray/services/obsolete/replicate.py
tryon_tray/services/video/__init__.py
tryon_tray/services/video/kling.py
tryon_tray/services/vton/__init__.py
tryon_tray/services/vton/alphabake.py
tryon_tray/services/vton/fashnai.py
tryon_tray/services/vton/klingai.py
tryon_tray/services/vton/replicate.py
tryon_tray/services/vton/vmodel.py
tryon_tray/types/video.py
tryon_tray/types/vton.py
tryon_tray/utils/config.py
tryon_tray/utils/discovery.py
tryon_tray/utils/file_io.py
tryon_tray-0.2.4.1.dist-info/METADATA
tryon_tray-0.2.4.1.dist-info/WHEEL
tryon_tray-0.2.4.1.dist-info/top_level.txt
tryon_tray-0.2.4.1.dist-info/RECORD
