Metadata-Version: 2.4
Name: tryon-tray
Version: 0.2.4.1
Summary: A package for virtual try-on services integration
Home-page: https://www.alphabake.io/
Author: Nitish Reddy Parvatham
Author-email: nitish@alphabake.io
Classifier: Development Status :: 3 - Alpha
Classifier: Intended Audience :: Developers
Classifier: License :: OSI Approved :: MIT License
Classifier: Operating System :: OS Independent
Classifier: Programming Language :: Python :: 3
Classifier: Programming Language :: Python :: 3.7
Classifier: Programming Language :: Python :: 3.8
Classifier: Programming Language :: Python :: 3.9
Requires-Python: >=3.7
Requires-Dist: requests
Requires-Dist: python-dotenv
Requires-Dist: tqdm
Requires-Dist: pyjwt
Requires-Dist: replicate
Dynamic: author
Dynamic: author-email
Dynamic: classifier
Dynamic: description
Dynamic: description-content-type
Dynamic: home-page
Dynamic: requires-dist
Dynamic: requires-python
Dynamic: summary
